README.md
setup.cfg
setup.py
syncany/__init__.py
syncany/errors.py
syncany/hook.py
syncany/logger.py
syncany/main.py
syncany/utils.py
syncany.egg-info/PKG-INFO
syncany.egg-info/SOURCES.txt
syncany.egg-info/dependency_links.txt
syncany.egg-info/entry_points.txt
syncany.egg-info/not-zip-safe
syncany.egg-info/requires.txt
syncany.egg-info/top_level.txt
syncany/calculaters/__init__.py
syncany/calculaters/builtin.py
syncany/calculaters/calculater.py
syncany/calculaters/convert_calculater.py
syncany/calculaters/datetime_calculater.py
syncany/calculaters/import_calculater.py
syncany/calculaters/textline_calculater.py
syncany/calculaters/transform_calculater.py
syncany/database/__init__.py
syncany/database/beanstalk.py
syncany/database/clickhouse.py
syncany/database/csv.py
syncany/database/database.py
syncany/database/elasticsearch.py
syncany/database/excel.py
syncany/database/http.py
syncany/database/influxdb.py
syncany/database/json.py
syncany/database/memory.py
syncany/database/mongodb.py
syncany/database/mysql.py
syncany/database/oracle.py
syncany/database/postgresql.py
syncany/database/redis.py
syncany/database/sqlite.py
syncany/database/sqlserver.py
syncany/database/textline.py
syncany/filters/__init__.py
syncany/filters/builtin.py
syncany/filters/filter.py
syncany/loaders/__init__.py
syncany/loaders/cache.py
syncany/loaders/calculate_db.py
syncany/loaders/calculate_db_join.py
syncany/loaders/const.py
syncany/loaders/db.py
syncany/loaders/db_join.py
syncany/loaders/db_pull.py
syncany/loaders/loader.py
syncany/outputers/__init__.py
syncany/outputers/db.py
syncany/outputers/db_delete_insert.py
syncany/outputers/db_insert.py
syncany/outputers/db_update.py
syncany/outputers/db_update_delete_insert.py
syncany/outputers/db_update_insert.py
syncany/outputers/outputer.py
syncany/taskers/__init__.py
syncany/taskers/context.py
syncany/taskers/iterator.py
syncany/taskers/manager.py
syncany/taskers/tasker.py
syncany/taskers/config/__init__.py
syncany/taskers/config/file_reader.py
syncany/taskers/config/http_reader.py
syncany/taskers/config/json_parser.py
syncany/taskers/config/parser.py
syncany/taskers/config/reader.py
syncany/taskers/config/yaml_parser.py
syncany/taskers/core/__init__.py
