Metadata-Version: 2.1
Name: syncany
Version: 0.2.28
Summary: 简单易用的数据同步转换导出框架
Home-page: https://github.com/snower/syncany
Author: snower
Author-email: sujian199@gmail.com
License: MIT
Platform: UNKNOWN
Provides-Extra: clickhouse
Provides-Extra: elasticsearch
Provides-Extra: influxdb
Provides-Extra: openpyxl
Provides-Extra: oracledb
Provides-Extra: postgresql
Provides-Extra: pymongo
Provides-Extra: pymssql
Provides-Extra: pymysql
Provides-Extra: redis
Provides-Extra: requests
Provides-Extra: rich
